{
  "annotations": {
    "list": [
      {
        "builtIn": 1,
        "datasource": {
          "type": "grafana",
          "uid": "-- Grafana --"
        },
        "enable": true,
        "hide": true,
        "iconColor": "rgba(0, 211, 255, 1)",
        "name": "Annotations & Alerts",
        "type": "dashboard"
      }
    ]
  },
  "editable": true,
  "panels": [
    {
      "datasource": {
        "type": "prometheus",
        "uid": "${DS_PROMETHEUS}"
      },
      "fieldConfig": {
        "defaults": {
          "color": {
            "mode": "thresholds"
          },
          "thresholds": {
            "mode": "absolute",
            "steps": [
              {
                "color": "red",
                "value": null
              },
              {
                "color": "green",
                "value": 1
              }
            ]
          }
        },
        "overrides": []
      },
      "gridPos": {
        "h": 8,
        "w": 6,
        "x": 0,
        "y": 0
      },
      "id": 1,
      "options": {
        "colorMode": "background",
        "graphMode": "none",
        "justifyMode": "center",
        "orientation": "auto",
        "reduceOptions": {
          "calcs": [
            "lastNotNull"
          ],
          "fields": "",
          "values": false
        }
      },
      "targets": [
        {
          "expr": "sum(up{service=~\"weather-app-(blue|green)\"})",
          "refId": "A"
        }
      ],
      "title": "Scrape Targets Up",
      "type": "stat"
    },
    {
      "datasource": {
        "type": "prometheus",
        "uid": "${DS_PROMETHEUS}"
      },
      "fieldConfig": {
        "defaults": {
          "color": {
            "mode": "palette-classic"
          },
          "unit": "reqps"
        },
        "overrides": []
      },
      "gridPos": {
        "h": 8,
        "w": 9,
        "x": 6,
        "y": 0
      },
      "id": 2,
      "targets": [
        {
          "expr": "sum(rate(weather_lookup_requests_total[5m]))",
          "legendFormat": "lookups",
          "refId": "A"
        }
      ],
      "title": "Lookup Request Rate",
      "type": "timeseries"
    },
    {
      "datasource": {
        "type": "prometheus",
        "uid": "${DS_PROMETHEUS}"
      },
      "fieldConfig": {
        "defaults": {
          "color": {
            "mode": "palette-classic"
          },
          "unit": "short"
        },
        "overrides": []
      },
      "gridPos": {
        "h": 8,
        "w": 9,
        "x": 15,
        "y": 0
      },
      "id": 3,
      "targets": [
        {
          "expr": "sum(rate(weather_lookup_not_found_total[5m]))",
          "legendFormat": "not_found",
          "refId": "A"
        },
        {
          "expr": "sum(rate(weather_lookup_bad_requests_total[5m]))",
          "legendFormat": "bad_request",
          "refId": "B"
        }
      ],
      "title": "Failed Lookup Rate",
      "type": "timeseries"
    },
    {
      "datasource": {
        "type": "prometheus",
        "uid": "${DS_PROMETHEUS}"
      },
      "fieldConfig": {
        "defaults": {
          "color": {
            "mode": "palette-classic"
          },
          "unit": "ms"
        },
        "overrides": []
      },
      "gridPos": {
        "h": 9,
        "w": 12,
        "x": 0,
        "y": 8
      },
      "id": 4,
      "targets": [
        {
          "expr": "histogram_quantile(0.95, sum by (le) (rate(weather_lookup_duration_ms_bucket[5m])))",
          "legendFormat": "p95",
          "refId": "A"
        },
        {
          "expr": "histogram_quantile(0.50, sum by (le) (rate(weather_lookup_duration_ms_bucket[5m])))",
          "legendFormat": "p50",
          "refId": "B"
        }
      ],
      "title": "Lookup Latency",
      "type": "timeseries"
    },
    {
      "datasource": {
        "type": "prometheus",
        "uid": "${DS_PROMETHEUS}"
      },
      "fieldConfig": {
        "defaults": {
          "color": {
            "mode": "palette-classic"
          },
          "unit": "short"
        },
        "overrides": []
      },
      "gridPos": {
        "h": 9,
        "w": 12,
        "x": 12,
        "y": 8
      },
      "id": 5,
      "targets": [
        {
          "expr": "sum by (city) (rate(weather_lookup_requests_total[5m]))",
          "legendFormat": "{{city}}",
          "refId": "A"
        }
      ],
      "title": "Lookup Rate by City",
      "type": "timeseries"
    }
  ],
  "refresh": "15s",
  "schemaVersion": 39,
  "style": "dark",
  "tags": [
    "weather-app",
    "prometheus"
  ],
  "templating": {
    "list": []
  },
  "time": {
    "from": "now-30m",
    "to": "now"
  },
  "title": "Weather App Metrics",
  "version": 1
}